{
    "docId": "Test_Tweets",
    "language": "en",
    "matches": [
        {
            "charLength": 2,
            "charOffset": 0,
            "text": "A ",
            "entity": {}
        },
        {
            "charLength": 14,
            "charOffset": 195,
            "text": "Marilyn Monroe",
            "entity": {
                "id": "http://www.wikidata.org/entity/Q4616",
                "confidence": 0.9961588245355136
            }
        },
        {
            "charLength": 15,
            "charOffset": 256,
            "text": "Abraham Lincoln",
            "entity": {
                "id": "http://www.wikidata.org/entity/Q91",
                "confidence": 0.971971222561059
            }
        },
        {
            "charLength": 2,
            "charOffset": 286,
            "text": "US",
            "entity": {}
        },
        {
            "charLength": 13,
            "charOffset": 325,
            "text": "Mother Teresa",
            "entity": {
                "id": "http://www.wikidata.org/entity/Q30547",
                "confidence": 1
            }
        },
        {
            "charLength": 19,
            "charOffset": 353,
            "text": "Macedonian Catholic",
            "entity": {}
        },
        {
            "charLength": 15,
            "charOffset": 388,
            "text": "John F. Kennedy",
            "entity": {
                "id": "http://www.wikidata.org/entity/Q9696",
                "confidence": 0.9661465224374246
            }
        },
        {
            "charLength": 2,
            "charOffset": 418,
            "text": "US",
            "entity": {}
        },
        {
            "charLength": 18,
            "charOffset": 443,
            "text": "Martin Luther King",
            "entity": {
                "id": "http://www.wikidata.org/entity/Q8027",
                "confidence": 0.9923085249705855
            }
        },
        {
            "charLength": 14,
            "charOffset": 510,
            "text": "Nelson Mandela",
            "entity": {
                "id": "http://www.wikidata.org/entity/Q8023",
                "confidence": 0.9972906477671415
            }
        },
        {
            "charLength": 18,
            "charOffset": 590,
            "text": "Queen Elizabeth II",
            "entity": {
                "id": "http://www.wikidata.org/entity/Q9682",
                "confidence": 1
            }
        },
        {
            "charLength": 17,
            "charOffset": 646,
            "text": "Winston Churchill",
            "entity": {
                "id": "http://www.wikidata.org/entity/Q8016",
                "confidence": 0.9850370851009586
            }
        },
        {
            "charLength": 12,
            "charOffset": 713,
            "text": "Donald Trump",
            "entity": {
                "id": "http://www.wikidata.org/entity/Q22686",
                "confidence": 0.9863792427909835
            }
        },
        {
            "charLength": 10,
            "charOffset": 760,
            "text": "Bill Gates",
            "entity": {
                "id": "http://www.wikidata.org/entity/Q5284",
                "confidence": 0.7064521328925736
            }
        },
        {
            "charLength": 9,
            "charOffset": 814,
            "text": "Microsoft",
            "entity": {
                "id": "http://www.wikidata.org/entity/Q2283",
                "confidence": 0.9815668554750575
            }
        },
        {
            "charLength": 12,
            "charOffset": 824,
            "text": "Muhammad Ali",
            "entity": {
                "id": "http://www.wikidata.org/entity/Q36107",
                "confidence": 0.9340101198168878
            }
        },
        {
            "charLength": 5,
            "charOffset": 860,
            "text": "Boxer",
            "entity": {
                "id": "http://www.wikidata.org/entity/Q150229",
                "confidence": 0.22377460079737224
            }
        },
        {
            "charLength": 14,
            "charOffset": 894,
            "text": "Mahatma Gandhi",
            "entity": {
                "id": "http://www.wikidata.org/entity/Q1001",
                "confidence": 0.9991129186855254
            }
        },
        {
            "charLength": 17,
            "charOffset": 962,
            "text": "Margaret Thatcher",
            "entity": {
                "id": "http://www.wikidata.org/entity/Q7416",
                "confidence": 1
            }
        },
        {
            "charLength": 20,
            "charOffset": 1029,
            "text": "Christopher Columbus",
            "entity": {
                "id": "http://www.wikidata.org/entity/Q7322",
                "confidence": 0.9674631780115057
            }
        },
        {
            "charLength": 14,
            "charOffset": 1081,
            "text": "Charles Darwin",
            "entity": {
                "id": "http://www.wikidata.org/entity/Q1035",
                "confidence": 0.9960192583751626
            }
        },
        {
            "charLength": 13,
            "charOffset": 1149,
            "text": "Elvis Presley",
            "entity": {
                "id": "http://www.wikidata.org/entity/Q303",
                "confidence": 0.9973742625989931
            }
        },
        {
            "charLength": 15,
            "charOffset": 1195,
            "text": "Albert Einstein",
            "entity": {
                "id": "http://www.wikidata.org/entity/Q937",
                "confidence": 0.9976666669666184
            }
        },
        {
            "charLength": 14,
            "charOffset": 1264,
            "text": "Paul McCartney",
            "entity": {
                "id": "http://www.wikidata.org/entity/Q2599",
                "confidence": 1
            }
        },
        {
            "charLength": 8,
            "charOffset": 1331,
            "text": "Victoria",
            "entity": {
                "id": "http://www.wikidata.org/entity/Q9439",
                "confidence": 0.08928517111869476
            }
        },
        {
            "charLength": 12,
            "charOffset": 1383,
            "text": "Pope Francis",
            "entity": {
                "id": "http://www.wikidata.org/entity/Q450675",
                "confidence": 1
            }
        },
        {
            "charLength": 16,
            "charOffset": 1435,
            "text": "Jawaharlal Nehru",
            "entity": {
                "id": "http://www.wikidata.org/entity/Q1047",
                "confidence": 1
            }
        },
        {
            "charLength": 17,
            "charOffset": 1500,
            "text": "Leonardo da Vinci",
            "entity": {
                "id": "http://www.wikidata.org/entity/Q762",
                "confidence": 0.9913966811390056
            }
        },
        {
            "charLength": 16,
            "charOffset": 1570,
            "text": "Vincent Van Gogh",
            "entity": {
                "id": "http://www.wikidata.org/entity/Q5582",
                "confidence": 0.9974487353859566
            }
        },
        {
            "charLength": 21,
            "charOffset": 1614,
            "text": "Franklin D. Roosevelt",
            "entity": {
                "id": "http://www.wikidata.org/entity/Q8007",
                "confidence": 0.9899472714087076
            }
        },
        {
            "charLength": 2,
            "charOffset": 1650,
            "text": "US",
            "entity": {}
        },
        {
            "charLength": 12,
            "charOffset": 1680,
            "text": "John Paul II",
            "entity": {
                "id": "http://www.wikidata.org/entity/Q989",
                "confidence": 0.9735424295760124
            }
        },
        {
            "charLength": 13,
            "charOffset": 1719,
            "text": "Thomas Edison",
            "entity": {
                "id": "http://www.wikidata.org/entity/Q8743",
                "confidence": 0.9950161340993149
            }
        },
        {
            "charLength": 10,
            "charOffset": 1766,
            "text": "Rosa Parks",
            "entity": {
                "id": "http://www.wikidata.org/entity/Q41921",
                "confidence": 0.9872142086896021
            }
        },
        {
            "charLength": 16,
            "charOffset": 1823,
            "text": "Aung San Suu Kyi",
            "entity": {
                "id": "http://www.wikidata.org/entity/Q36740",
                "confidence": 1
            }
        },
        {
            "charLength": 14,
            "charOffset": 1876,
            "text": "Lyndon Johnson",
            "entity": {
                "id": "http://www.wikidata.org/entity/Q9640",
                "confidence": 1
            }
        },
        {
            "charLength": 2,
            "charOffset": 1905,
            "text": "US",
            "entity": {}
        },
        {
            "charLength": 16,
            "charOffset": 1930,
            "text": "Ludwig Beethoven",
            "entity": {
                "id": "http://www.wikidata.org/entity/Q255",
                "confidence": 0.9624471830069544
            }
        },
        {
            "charLength": 13,
            "charOffset": 1977,
            "text": "Oprah Winfrey",
            "entity": {
                "id": "http://www.wikidata.org/entity/Q55800",
                "confidence": 0.9930201533488012
            }
        },
        {
            "charLength": 11,
            "charOffset": 2001,
            "text": "American TV",
            "entity": {}
        },
        {
            "charLength": 13,
            "charOffset": 2046,
            "text": "Indira Gandhi",
            "entity": {
                "id": "http://www.wikidata.org/entity/Q1149",
                "confidence": 1
            }
        },
        {
            "charLength": 5,
            "charOffset": 2092,
            "text": "India",
            "entity": {
                "id": "http://www.wikidata.org/entity/Q668",
                "confidence": 0.7461009524494403
            }
        },
        {
            "charLength": 9,
            "charOffset": 2110,
            "text": "Eva Peron",
            "entity": {
                "id": "http://www.wikidata.org/entity/Q40933",
                "confidence": 1
            }
        },
        {
            "charLength": 9,
            "charOffset": 2148,
            "text": "Argentina",
            "entity": {
                "id": "http://www.wikidata.org/entity/Q414",
                "confidence": 0.7934256186760389
            }
        },
        {
            "charLength": 14,
            "charOffset": 2170,
            "text": "Benazir Bhutto",
            "entity": {
                "id": "http://www.wikidata.org/entity/Q34413",
                "confidence": 1
            }
        },
        {
            "charLength": 8,
            "charOffset": 2217,
            "text": "Pakistan",
            "entity": {
                "id": "http://www.wikidata.org/entity/Q843",
                "confidence": 0.8931872727421589
            }
        },
        {
            "charLength": 13,
            "charOffset": 2238,
            "text": "George Orwell",
            "entity": {
                "id": "http://www.wikidata.org/entity/Q3335",
                "confidence": 1
            }
        },
        {
            "charLength": 12,
            "charOffset": 2281,
            "text": "Desmond Tutu",
            "entity": {
                "id": "http://www.wikidata.org/entity/Q43033",
                "confidence": 1
            }
        },
        {
            "charLength": 11,
            "charOffset": 2415,
            "text": "Walt Disney",
            "entity": {
                "id": "http://www.wikidata.org/entity/Q8704",
                "confidence": 0.8919454021812817
            }
        },
        {
            "charLength": 14,
            "charOffset": 2464,
            "text": "Neil Armstrong",
            "entity": {
                "id": "http://www.wikidata.org/entity/Q1615",
                "confidence": 0.990841400487319
            }
        },
        {
            "charLength": 2,
            "charOffset": 2493,
            "text": "US",
            "entity": {}
        },
        {
            "charLength": 13,
            "charOffset": 2506,
            "text": "Peter Sellers",
            "entity": {
                "id": "http://www.wikidata.org/entity/Q177984",
                "confidence": 0.9997511848384926
            }
        },
        {
            "charLength": 12,
            "charOffset": 2561,
            "text": "Barack Obama",
            "entity": {
                "id": "http://www.wikidata.org/entity/Q76",
                "confidence": 0.9922566227882357
            }
        },
        {
            "charLength": 2,
            "charOffset": 2584,
            "text": "US",
            "entity": {}
        },
        {
            "charLength": 9,
            "charOffset": 2609,
            "text": "Malcolm X",
            "entity": {
                "id": "http://www.wikidata.org/entity/Q43303",
                "confidence": 0.9045575329280463
            }
        },
        {
            "charLength": 14,
            "charOffset": 2633,
            "text": "American Black",
            "entity": {}
        },
        {
            "charLength": 15,
            "charOffset": 2704,
            "text": "Richard Branson",
            "entity": {
                "id": "http://www.wikidata.org/entity/Q194419",
                "confidence": 1
            }
        },
        {
            "charLength": 4,
            "charOffset": 2751,
            "text": "Pele",
            "entity": {
                "id": "http://www.wikidata.org/entity/Q12897",
                "confidence": 0.47615632698128013
            }
        },
        {
            "charLength": 14,
            "charOffset": 2825,
            "text": "Angelina Jolie",
            "entity": {
                "id": "http://www.wikidata.org/entity/Q13909",
                "confidence": 1
            }
        },
        {
            "charLength": 11,
            "charOffset": 2882,
            "text": "Jesse Owens",
            "entity": {
                "id": "http://www.wikidata.org/entity/Q52651",
                "confidence": 0.9995056635588765
            }
        },
        {
            "charLength": 2,
            "charOffset": 2908,
            "text": "US",
            "entity": {}
        },
        {
            "charLength": 16,
            "charOffset": 2940,
            "text": "Ernest Hemingway",
            "entity": {
                "id": "http://www.wikidata.org/entity/Q23434",
                "confidence": 1
            }
        },
        {
            "charLength": 11,
            "charOffset": 2987,
            "text": "John Lennon",
            "entity": {
                "id": "http://www.wikidata.org/entity/Q1203",
                "confidence": 0.9943545068129245
            }
        },
        {
            "charLength": 18,
            "charOffset": 3045,
            "text": "Beatles Henry Ford",
            "entity": {}
        },
        {
            "charLength": 2,
            "charOffset": 3078,
            "text": "US",
            "entity": {}
        },
        {
            "charLength": 14,
            "charOffset": 3095,
            "text": "Haile Selassie",
            "entity": {
                "id": "http://www.wikidata.org/entity/Q41178",
                "confidence": 1
            }
        },
        {
            "charLength": 8,
            "charOffset": 3135,
            "text": "Ethiopia",
            "entity": {
                "id": "http://www.wikidata.org/entity/Q115",
                "confidence": 0.9408543750682733
            }
        },
        {
            "charLength": 13,
            "charOffset": 3156,
            "text": "Joseph Stalin",
            "entity": {
                "id": "http://www.wikidata.org/entity/Q855",
                "confidence": 0.9985543426155574
            }
        },
        {
            "charLength": 12,
            "charOffset": 3194,
            "text": "Soviet Union",
            "entity": {
                "id": "http://www.wikidata.org/entity/Q15180",
                "confidence": 0.8792109437199461
            }
        },
        {
            "charLength": 12,
            "charOffset": 3224,
            "text": "Baden Powell",
            "entity": {
                "id": "http://www.wikidata.org/entity/Q12665",
                "confidence": 0.6429042931380118
            }
        },
        {
            "charLength": 14,
            "charOffset": 3285,
            "text": "Michael Jordon",
            "entity": {
                "id": "http://www.wikidata.org/entity/Q41421",
                "confidence": 1
            }
        },
        {
            "charLength": 2,
            "charOffset": 3310,
            "text": "US",
            "entity": {}
        },
        {
            "charLength": 15,
            "charOffset": 3329,
            "text": "George Bush Jnr",
            "entity": {}
        },
        {
            "charLength": 2,
            "charOffset": 3355,
            "text": "US",
            "entity": {}
        },
        {
            "charLength": 14,
            "charOffset": 3378,
            "text": "Vladimir Lenin",
            "entity": {
                "id": "http://www.wikidata.org/entity/Q1394",
                "confidence": 1
            }
        },
        {
            "charLength": 14,
            "charOffset": 3441,
            "text": "Ingrid Bergman",
            "entity": {
                "id": "http://www.wikidata.org/entity/Q43247",
                "confidence": 0.999797883834313
            }
        },
        {
            "charLength": 12,
            "charOffset": 3486,
            "text": "Fidel Castro",
            "entity": {
                "id": "http://www.wikidata.org/entity/Q11256",
                "confidence": 0.9998800967458764
            }
        },
        {
            "charLength": 4,
            "charOffset": 3522,
            "text": "Cuba",
            "entity": {
                "id": "http://www.wikidata.org/entity/Q241",
                "confidence": 0.8867332161073903
            }
        },
        {
            "charLength": 11,
            "charOffset": 3539,
            "text": "Leo Tolstoy",
            "entity": {
                "id": "http://www.wikidata.org/entity/Q7243",
                "confidence": 1
            }
        },
        {
            "charLength": 13,
            "charOffset": 3596,
            "text": "Pablo Picasso",
            "entity": {
                "id": "http://www.wikidata.org/entity/Q5593",
                "confidence": 0.998252774574964
            }
        },
        {
            "charLength": 11,
            "charOffset": 3646,
            "text": "Oscar Wilde",
            "entity": {
                "id": "http://www.wikidata.org/entity/Q30875",
                "confidence": 0.9874503133906534
            }
        },
        {
            "charLength": 11,
            "charOffset": 3703,
            "text": "Coco Chanel",
            "entity": {
                "id": "http://www.wikidata.org/entity/Q45661",
                "confidence": 0.9810325373779147
            }
        },
        {
            "charLength": 17,
            "charOffset": 3753,
            "text": "Charles de Gaulle",
            "entity": {
                "id": "http://www.wikidata.org/entity/Q2042",
                "confidence": 0.9803806501932936
            }
        },
        {
            "charLength": 14,
            "charOffset": 3836,
            "text": "Amelia Earhart",
            "entity": {
                "id": "http://www.wikidata.org/entity/Q3355",
                "confidence": 0.9936856414256092
            }
        },
        {
            "charLength": 13,
            "charOffset": 3873,
            "text": "John M Keynes",
            "entity": {
                "id": "http://www.wikidata.org/entity/Q9317",
                "confidence": 1
            }
        },
        {
            "charLength": 13,
            "charOffset": 3919,
            "text": "Louis Pasteur",
            "entity": {
                "id": "http://www.wikidata.org/entity/Q529",
                "confidence": 0.975578723661563
            }
        },
        {
            "charLength": 17,
            "charOffset": 3981,
            "text": "Mikhail Gorbachev",
            "entity": {
                "id": "http://www.wikidata.org/entity/Q30487",
                "confidence": 1
            }
        },
        {
            "charLength": 12,
            "charOffset": 4019,
            "text": "Soviet Union",
            "entity": {
                "id": "http://www.wikidata.org/entity/Q15180",
                "confidence": 0.8792109437199461
            }
        },
        {
            "charLength": 5,
            "charOffset": 4044,
            "text": "Plato",
            "entity": {
                "id": "http://www.wikidata.org/entity/Q859",
                "confidence": 0.9487521205001926
            }
        },
        {
            "charLength": 12,
            "charOffset": 4086,
            "text": "Adolf Hitler",
            "entity": {
                "id": "http://www.wikidata.org/entity/Q352",
                "confidence": 0.9979946438556528
            }
        },
        {
            "charLength": 4,
            "charOffset": 4123,
            "text": "Nazi",
            "entity": {
                "id": "http://www.wikidata.org/entity/Q183",
                "confidence": 0.3662946957711834
            }
        },
        {
            "charLength": 7,
            "charOffset": 4128,
            "text": "Germany",
            "entity": {
                "id": "http://www.wikidata.org/entity/Q183",
                "confidence": 0.5821776929781163
            }
        },
        {
            "charLength": 14,
            "charOffset": 4181,
            "text": "Mary Magdalene",
            "entity": {
                "id": "http://www.wikidata.org/entity/Q63070",
                "confidence": 0.9883956737586154
            }
        },
        {
            "charLength": 3,
            "charOffset": 4199,
            "text": "BCE",
            "entity": {
                "id": "http://www.wikidata.org/entity/Q208141",
                "confidence": 0.39664147701925756
            }
        },
        {
            "charLength": 29,
            "charOffset": 4222,
            "text": "Jesus Christ Alfred Hitchcock",
            "entity": {}
        },
        {
            "charLength": 15,
            "charOffset": 4309,
            "text": "Michael Jackson",
            "entity": {
                "id": "http://www.wikidata.org/entity/Q2831",
                "confidence": 0.9789794120172176
            }
        },
        {
            "charLength": 7,
            "charOffset": 4357,
            "text": "Madonna",
            "entity": {
                "id": "http://www.wikidata.org/entity/Q1744",
                "confidence": 0.9010817093267909
            }
        },
        {
            "charLength": 9,
            "charOffset": 4410,
            "text": "Mata Hari",
            "entity": {
                "id": "http://www.wikidata.org/entity/Q82180",
                "confidence": 0.45409782469709564
            }
        },
        {
            "charLength": 9,
            "charOffset": 4471,
            "text": "Cleopatra",
            "entity": {
                "id": "http://www.wikidata.org/entity/Q4430",
                "confidence": 0.1522399913974538
            }
        },
        {
            "charLength": 5,
            "charOffset": 4504,
            "text": "Egypt",
            "entity": {
                "id": "http://www.wikidata.org/entity/Q79",
                "confidence": 0.8662929181608632
            }
        },
        {
            "charLength": 11,
            "charOffset": 4510,
            "text": "Grace Kelly",
            "entity": {
                "id": "http://www.wikidata.org/entity/Q3925",
                "confidence": 0.9460157927412715
            }
        },
        {
            "charLength": 17,
            "charOffset": 4566,
            "text": "Monaco Steve Jobs",
            "entity": {}
        },
        {
            "charLength": 5,
            "charOffset": 4612,
            "text": "Apple",
            "entity": {
                "id": "http://www.wikidata.org/entity/Q312",
                "confidence": 0.9198005617114392
            }
        },
        {
            "charLength": 13,
            "charOffset": 4628,
            "text": "Ronald Reagan",
            "entity": {
                "id": "http://www.wikidata.org/entity/Q9960",
                "confidence": 0.997382160999289
            }
        },
        {
            "charLength": 2,
            "charOffset": 4656,
            "text": "US",
            "entity": {}
        },
        {
            "charLength": 12,
            "charOffset": 4679,
            "text": "Lionel Messi",
            "entity": {
                "id": "http://www.wikidata.org/entity/Q615",
                "confidence": 1
            }
        },
        {
            "charLength": 9,
            "charOffset": 4725,
            "text": "Babe Ruth",
            "entity": {
                "id": "http://www.wikidata.org/entity/Q213812",
                "confidence": 0.9899703948673053
            }
        },
        {
            "charLength": 10,
            "charOffset": 4774,
            "text": "Bob Geldof",
            "entity": {
                "id": "http://www.wikidata.org/entity/Q216608",
                "confidence": 1
            }
        },
        {
            "charLength": 12,
            "charOffset": 4826,
            "text": "Leon Trotsky",
            "entity": {
                "id": "http://www.wikidata.org/entity/Q33391",
                "confidence": 1
            }
        },
        {
            "charLength": 13,
            "charOffset": 4883,
            "text": "Roger Federer",
            "entity": {
                "id": "http://www.wikidata.org/entity/Q1426",
                "confidence": 1
            }
        },
        {
            "charLength": 13,
            "charOffset": 4927,
            "text": "Sigmund Freud",
            "entity": {
                "id": "http://www.wikidata.org/entity/Q9215",
                "confidence": 1
            }
        },
        {
            "charLength": 14,
            "charOffset": 4978,
            "text": "Woodrow Wilson",
            "entity": {
                "id": "http://www.wikidata.org/entity/Q34296",
                "confidence": 0.9875713950542431
            }
        },
        {
            "charLength": 2,
            "charOffset": 5007,
            "text": "US",
            "entity": {}
        },
        {
            "charLength": 10,
            "charOffset": 5032,
            "text": "Mao Zedong",
            "entity": {
                "id": "http://www.wikidata.org/entity/Q5816",
                "confidence": 0.999559549092864
            }
        },
        {
            "charLength": 17,
            "charOffset": 5096,
            "text": "Katherine Hepburn",
            "entity": {
                "id": "http://www.wikidata.org/entity/Q56016",
                "confidence": 1
            }
        },
        {
            "charLength": 14,
            "charOffset": 5145,
            "text": "Audrey Hepburn",
            "entity": {
                "id": "http://www.wikidata.org/entity/Q42786",
                "confidence": 1
            }
        },
        {
            "charLength": 13,
            "charOffset": 5207,
            "text": "David Beckham",
            "entity": {
                "id": "http://www.wikidata.org/entity/Q10520",
                "confidence": 1
            }
        },
        {
            "charLength": 11,
            "charOffset": 5251,
            "text": "Tiger Woods",
            "entity": {
                "id": "http://www.wikidata.org/entity/Q10993",
                "confidence": 1
            }
        },
        {
            "charLength": 10,
            "charOffset": 5289,
            "text": "Usain Bolt",
            "entity": {
                "id": "http://www.wikidata.org/entity/Q1189",
                "confidence": 1
            }
        },
        {
            "charLength": 10,
            "charOffset": 5340,
            "text": "Carl Lewis",
            "entity": {
                "id": "http://www.wikidata.org/entity/Q131237",
                "confidence": 1
            }
        },
        {
            "charLength": 2,
            "charOffset": 5361,
            "text": "US",
            "entity": {}
        },
        {
            "charLength": 7,
            "charOffset": 5392,
            "text": "Charles",
            "entity": {}
        },
        {
            "charLength": 26,
            "charOffset": 5434,
            "text": "Jacqueline Kennedy Onassis",
            "entity": {
                "id": "http://www.wikidata.org/entity/Q165421",
                "confidence": 1
            }
        },
        {
            "charLength": 21,
            "charOffset": 5492,
            "text": "JF Kennedy C.S. Lewis",
            "entity": {}
        },
        {
            "charLength": 14,
            "charOffset": 5593,
            "text": "J.R.R. Tolkien",
            "entity": {
                "id": "http://www.wikidata.org/entity/Q892",
                "confidence": 1
            }
        },
        {
            "charLength": 16,
            "charOffset": 5637,
            "text": "Billie Jean King",
            "entity": {
                "id": "http://www.wikidata.org/entity/Q54527",
                "confidence": 1
            }
        },
        {
            "charLength": 10,
            "charOffset": 5713,
            "text": "Anne Frank",
            "entity": {
                "id": "http://www.wikidata.org/entity/Q4583",
                "confidence": 0.9930264267495117
            }
        }
    ],
    "entities": [
        {
            "id": "http://www.wikidata.org/entity/Q450675",
            "name": "Pope Francis",
            "url": "http://en.wikipedia.org/wiki/Pope%20Francis",
            "type": "PERSON",
            "salience": 0.08853274082782822
        },
        {
            "id": "http://www.wikidata.org/entity/Q1426",
            "name": "Roger Federer",
            "url": "http://en.wikipedia.org/wiki/Roger%20Federer",
            "type": "PERSON",
            "salience": 0.036528727842507665
        },
        {
            "id": "http://www.wikidata.org/entity/Q859",
            "name": "Plato",
            "url": "http://en.wikipedia.org/wiki/Plato",
            "type": "PERSON",
            "salience": 0.03097643961737695
        },
        {
            "id": "http://www.wikidata.org/entity/Q989",
            "name": "Pope John Paul II",
            "url": "http://en.wikipedia.org/wiki/Pope%20John%20Paul%20II",
            "type": "PERSON",
            "salience": 0.056001325902750615
        },
        {
            "id": "http://www.wikidata.org/entity/Q1394",
            "name": "Vladimir Lenin",
            "url": "http://en.wikipedia.org/wiki/Vladimir%20Lenin",
            "type": "PERSON",
            "salience": 0.038255844904526166
        },
        {
            "id": "http://www.wikidata.org/entity/Q5593",
            "name": "Pablo Picasso",
            "url": "http://en.wikipedia.org/wiki/Pablo%20Picasso",
            "type": "PERSON",
            "salience": 0.030229464887870986
        },
        {
            "id": "http://www.wikidata.org/entity/Q7416",
            "name": "Margaret Thatcher",
            "url": "http://en.wikipedia.org/wiki/Margaret%20Thatcher",
            "type": "PERSON",
            "salience": 0.15781774161992596
        },
        {
            "id": "http://www.wikidata.org/entity/Q1035",
            "name": "Charles Darwin",
            "url": "http://en.wikipedia.org/wiki/Charles%20Darwin",
            "type": "PERSON",
            "salience": 0.12657489910957562
        },
        {
            "id": "http://www.wikidata.org/entity/Q183",
            "name": "Germany",
            "url": "http://en.wikipedia.org/wiki/Germany",
            "type": "LOCATION",
            "salience": 0.046402246248953276
        },
        {
            "id": "http://www.wikidata.org/entity/Q8743",
            "name": "Thomas Edison",
            "url": "http://en.wikipedia.org/wiki/Thomas%20Edison",
            "type": "PERSON",
            "salience": 0.052269516005168146
        },
        {
            "id": "http://www.wikidata.org/entity/Q63070",
            "name": "Mary Magdalene",
            "url": "http://en.wikipedia.org/wiki/Mary%20Magdalene",
            "type": "PERSON",
            "salience": 0.02738533693365706
        },
        {
            "id": "http://www.wikidata.org/entity/Q3335",
            "name": "George Orwell",
            "url": "http://en.wikipedia.org/wiki/George%20Orwell",
            "type": "PERSON",
            "salience": 0.04571662091143225
        },
        {
            "id": "http://www.wikidata.org/entity/Q177984",
            "name": "Peter Sellers",
            "url": "http://en.wikipedia.org/wiki/Peter%20Sellers",
            "type": "PERSON",
            "salience": 0.03633056053113107
        },
        {
            "id": "http://www.wikidata.org/entity/Q9317",
            "name": "John Maynard Keynes",
            "url": "http://en.wikipedia.org/wiki/John%20Maynard%20Keynes",
            "type": "PERSON",
            "salience": 0.036920098320045565
        },
        {
            "id": "http://www.wikidata.org/entity/Q9439",
            "name": "Queen Victoria",
            "url": "http://en.wikipedia.org/wiki/Queen%20Victoria",
            "type": "PERSON",
            "salience": 0.11110752547931486
        },
        {
            "id": "http://www.wikidata.org/entity/Q54527",
            "name": "Billie Jean King",
            "url": "http://en.wikipedia.org/wiki/Billie%20Jean%20King",
            "type": "PERSON",
            "salience": 0.05895701307024804
        },
        {
            "id": "http://www.wikidata.org/entity/Q115",
            "name": "Ethiopia",
            "url": "http://en.wikipedia.org/wiki/Ethiopia",
            "type": "LOCATION",
            "salience": 0.03413717080995243
        },
        {
            "id": "http://www.wikidata.org/entity/Q5582",
            "name": "Vincent van Gogh",
            "url": "http://en.wikipedia.org/wiki/Vincent%20van%20Gogh",
            "type": "PERSON",
            "salience": 0.05903212250132109
        },
        {
            "id": "http://www.wikidata.org/entity/Q7243",
            "name": "Leo Tolstoy",
            "url": "http://en.wikipedia.org/wiki/Leo%20Tolstoy",
            "type": "PERSON",
            "salience": 0.03789936667613339
        },
        {
            "id": "http://www.wikidata.org/entity/Q2599",
            "name": "Paul McCartney",
            "url": "http://en.wikipedia.org/wiki/Paul%20McCartney",
            "type": "PERSON",
            "salience": 0.09640122560438324
        },
        {
            "id": "http://www.wikidata.org/entity/Q30547",
            "name": "Mother Teresa",
            "url": "http://en.wikipedia.org/wiki/Mother%20Teresa",
            "type": "PERSON",
            "salience": 0.2903780869930175
        },
        {
            "id": "http://www.wikidata.org/entity/Q1149",
            "name": "Indira Gandhi",
            "url": "http://en.wikipedia.org/wiki/Indira%20Gandhi",
            "type": "PERSON",
            "salience": 0.05410051572032202
        },
        {
            "id": "http://www.wikidata.org/entity/Q352",
            "name": "Adolf Hitler",
            "url": "http://en.wikipedia.org/wiki/Adolf%20Hitler",
            "type": "PERSON",
            "salience": 0.027047631597020214
        },
        {
            "id": "http://www.wikidata.org/entity/Q213812",
            "name": "Babe Ruth",
            "url": "http://en.wikipedia.org/wiki/Babe%20Ruth",
            "type": "PERSON",
            "salience": 0.027158272648830202
        },
        {
            "id": "http://www.wikidata.org/entity/Q216608",
            "name": "Bob Geldof",
            "url": "http://en.wikipedia.org/wiki/Bob%20Geldof",
            "type": "PERSON",
            "salience": 0.036528727842507665
        },
        {
            "id": "http://www.wikidata.org/entity/Q13909",
            "name": "Angelina Jolie",
            "url": "http://en.wikipedia.org/wiki/Angelina%20Jolie",
            "type": "PERSON",
            "salience": 0.040334443016093784
        },
        {
            "id": "http://www.wikidata.org/entity/Q131237",
            "name": "Carl Lewis",
            "url": "http://en.wikipedia.org/wiki/Carl%20Lewis",
            "type": "PERSON",
            "salience": 0.036363176785911944
        },
        {
            "id": "http://www.wikidata.org/entity/Q41421",
            "name": "Michael Jordan",
            "url": "http://en.wikipedia.org/wiki/Michael%20Jordan",
            "type": "PERSON",
            "salience": 0.03818675300641342
        },
        {
            "id": "http://www.wikidata.org/entity/Q23434",
            "name": "Ernest Hemingway",
            "url": "http://en.wikipedia.org/wiki/Ernest%20Hemingway",
            "type": "PERSON",
            "salience": 0.040334443016093784
        },
        {
            "id": "http://www.wikidata.org/entity/Q34296",
            "name": "Woodrow Wilson",
            "url": "http://en.wikipedia.org/wiki/Woodrow%20Wilson",
            "type": "PERSON",
            "salience": 0.02693893198938627
        },
        {
            "id": "http://www.wikidata.org/entity/Q241",
            "name": "Cuba",
            "url": "http://en.wikipedia.org/wiki/Cuba",
            "type": "LOCATION",
            "salience": 0.031793731499819365
        },
        {
            "id": "http://www.wikidata.org/entity/Q762",
            "name": "Leonardo da Vinci",
            "url": "http://en.wikipedia.org/wiki/Leonardo%20da%20Vinci",
            "type": "PERSON",
            "salience": 0.08070921922204555
        },
        {
            "id": "http://www.wikidata.org/entity/Q10520",
            "name": "David Beckham",
            "url": "http://en.wikipedia.org/wiki/David%20Beckham",
            "type": "PERSON",
            "salience": 0.036363176785911944
        },
        {
            "id": "http://www.wikidata.org/entity/Q12665",
            "name": "Robert Baden-Powell, 1st Baron Baden-Powell",
            "url": "http://en.wikipedia.org/wiki/Robert%20Baden-Powell%2C%201st%20Baron%20Baden-Powell",
            "type": "PERSON",
            "salience": 0.04331283144732752
        },
        {
            "id": "http://www.wikidata.org/entity/Q43033",
            "name": "Desmond Tutu",
            "url": "http://en.wikipedia.org/wiki/Desmond%20Tutu",
            "type": "PERSON",
            "salience": 0.04554323085800405
        },
        {
            "id": "http://www.wikidata.org/entity/Q76",
            "name": "Barack Obama",
            "url": "http://en.wikipedia.org/wiki/Barack%20Obama",
            "type": "PERSON",
            "salience": 0.036647780048068644
        },
        {
            "id": "http://www.wikidata.org/entity/Q529",
            "name": "Louis Pasteur",
            "url": "http://en.wikipedia.org/wiki/Louis%20Pasteur",
            "type": "PERSON",
            "salience": 0.03139421392829518
        },
        {
            "id": "http://www.wikidata.org/entity/Q79",
            "name": "Egypt",
            "url": "http://en.wikipedia.org/wiki/Egypt",
            "type": "LOCATION",
            "salience": 0.03302758979529748
        },
        {
            "id": "http://www.wikidata.org/entity/Q5284",
            "name": "Bill Gates",
            "url": "http://en.wikipedia.org/wiki/Bill%20Gates",
            "type": "PERSON",
            "salience": 0.2372500973055369
        },
        {
            "id": "http://www.wikidata.org/entity/Q414",
            "name": "Argentina",
            "url": "http://en.wikipedia.org/wiki/Argentina",
            "type": "LOCATION",
            "salience": 0.06671425829726763
        },
        {
            "id": "http://www.wikidata.org/entity/Q36740",
            "name": "Aung San Suu Kyi",
            "url": "http://en.wikipedia.org/wiki/Aung%20San%20Suu%20Kyi",
            "type": "PERSON",
            "salience": 0.05785376808041684
        },
        {
            "id": "http://www.wikidata.org/entity/Q9640",
            "name": "Lyndon B. Johnson",
            "url": "http://en.wikipedia.org/wiki/Lyndon%20B.%20Johnson",
            "type": "PERSON",
            "salience": 0.05441070877265685
        },
        {
            "id": "http://www.wikidata.org/entity/Q30487",
            "name": "Mikhail Gorbachev",
            "url": "http://en.wikipedia.org/wiki/Mikhail%20Gorbachev",
            "type": "PERSON",
            "salience": 0.036920098320045565
        },
        {
            "id": "http://www.wikidata.org/entity/Q1001",
            "name": "Mahatma Gandhi",
            "url": "http://en.wikipedia.org/wiki/Mahatma%20Gandhi",
            "type": "PERSON",
            "salience": 0.16699052959112412
        },
        {
            "id": "http://www.wikidata.org/entity/Q55800",
            "name": "Oprah Winfrey",
            "url": "http://en.wikipedia.org/wiki/Oprah%20Winfrey",
            "type": "PERSON",
            "salience": 0.043484555677088164
        },
        {
            "id": "http://www.wikidata.org/entity/Q36107",
            "name": "Muhammad Ali",
            "url": "http://en.wikipedia.org/wiki/Muhammad%20Ali",
            "type": "PERSON",
            "salience": 0.19463090550998025
        },
        {
            "id": "http://www.wikidata.org/entity/Q255",
            "name": "Ludwig van Beethoven",
            "url": "http://en.wikipedia.org/wiki/Ludwig%20van%20Beethoven",
            "type": "PERSON",
            "salience": 0.04672210596606711
        },
        {
            "id": "http://www.wikidata.org/entity/Q892",
            "name": "J. R. R. Tolkien",
            "url": "http://en.wikipedia.org/wiki/J.%20R.%20R.%20Tolkien",
            "type": "PERSON",
            "salience": 0.04833861182867164
        },
        {
            "id": "http://www.wikidata.org/entity/Q1744",
            "name": "Madonna (entertainer)",
            "url": "http://en.wikipedia.org/wiki/Madonna%20%28entertainer%29",
            "type": "PERSON",
            "salience": 0.032993531977303495
        },
        {
            "id": "http://www.wikidata.org/entity/Q3925",
            "name": "Grace Kelly",
            "url": "http://en.wikipedia.org/wiki/Grace%20Kelly",
            "type": "PERSON",
            "salience": 0.030978799766798525
        },
        {
            "id": "http://www.wikidata.org/entity/Q4616",
            "name": "Marilyn Monroe",
            "url": "http://en.wikipedia.org/wiki/Marilyn%20Monroe",
            "type": "PERSON",
            "salience": 0.2163171628341679
        },
        {
            "id": "http://www.wikidata.org/entity/Q52651",
            "name": "Jesse Owens",
            "url": "http://en.wikipedia.org/wiki/Jesse%20Owens",
            "type": "PERSON",
            "salience": 0.0356843521149538
        },
        {
            "id": "http://www.wikidata.org/entity/Q937",
            "name": "Albert Einstein",
            "url": "http://en.wikipedia.org/wiki/Albert%20Einstein",
            "type": "PERSON",
            "salience": 0.10531815203239477
        },
        {
            "id": "http://www.wikidata.org/entity/Q43303",
            "name": "Malcolm X",
            "url": "http://en.wikipedia.org/wiki/Malcolm%20X",
            "type": "PERSON",
            "salience": 0.04070151360077042
        },
        {
            "id": "http://www.wikidata.org/entity/Q22686",
            "name": "Donald Trump",
            "url": "http://en.wikipedia.org/wiki/Donald%20Trump",
            "type": "PERSON",
            "salience": 0.202040854089627
        },
        {
            "id": "http://www.wikidata.org/entity/Q41921",
            "name": "Rosa Parks",
            "url": "http://en.wikipedia.org/wiki/Rosa%20Parks",
            "type": "PERSON",
            "salience": 0.058876196509896284
        },
        {
            "id": "http://www.wikidata.org/entity/Q303",
            "name": "Elvis Presley",
            "url": "http://en.wikipedia.org/wiki/Elvis%20Presley",
            "type": "PERSON",
            "salience": 0.10520426658611051
        },
        {
            "id": "http://www.wikidata.org/entity/Q8027",
            "name": "Martin Luther King Jr.",
            "url": "http://en.wikipedia.org/wiki/Martin%20Luther%20King%20Jr.",
            "type": "PERSON",
            "salience": 0.2218885013459467
        },
        {
            "id": "http://www.wikidata.org/entity/Q2283",
            "name": "Microsoft",
            "url": "http://en.wikipedia.org/wiki/Microsoft",
            "type": "ORGANIZATION",
            "salience": 0.19013916068071446
        },
        {
            "id": "http://www.wikidata.org/entity/Q4583",
            "name": "Anne Frank",
            "url": "http://en.wikipedia.org/wiki/Anne%20Frank",
            "type": "PERSON",
            "salience": 0.03469960747949837
        },
        {
            "id": "http://www.wikidata.org/entity/Q8023",
            "name": "Nelson Mandela",
            "url": "http://en.wikipedia.org/wiki/Nelson%20Mandela",
            "type": "PERSON",
            "salience": 0.20518941856102246
        },
        {
            "id": "http://www.wikidata.org/entity/Q668",
            "name": "India",
            "url": "http://en.wikipedia.org/wiki/India",
            "type": "LOCATION",
            "salience": 0.08304074728817684
        },
        {
            "id": "http://www.wikidata.org/entity/Q2042",
            "name": "Charles de Gaulle",
            "url": "http://en.wikipedia.org/wiki/Charles%20de%20Gaulle",
            "type": "PERSON",
            "salience": 0.03144543735031029
        },
        {
            "id": "http://www.wikidata.org/entity/Q8704",
            "name": "Walt Disney",
            "url": "http://en.wikipedia.org/wiki/Walt%20Disney",
            "type": "PERSON",
            "salience": 0.04232911308464056
        },
        {
            "id": "http://www.wikidata.org/entity/Q30875",
            "name": "Oscar Wilde",
            "url": "http://en.wikipedia.org/wiki/Oscar%20Wilde",
            "type": "PERSON",
            "salience": 0.02941692937753939
        },
        {
            "id": "http://www.wikidata.org/entity/Q5816",
            "name": "Mao Zedong",
            "url": "http://en.wikipedia.org/wiki/Mao%20Zedong",
            "type": "PERSON",
            "salience": 0.028177740117069115
        },
        {
            "id": "http://www.wikidata.org/entity/Q1615",
            "name": "Neil Armstrong",
            "url": "http://en.wikipedia.org/wiki/Neil%20Armstrong",
            "type": "PERSON",
            "salience": 0.038792505841093776
        },
        {
            "id": "http://www.wikidata.org/entity/Q91",
            "name": "Abraham Lincoln",
            "url": "http://en.wikipedia.org/wiki/Abraham%20Lincoln",
            "type": "PERSON",
            "salience": 0.22467871350171997
        },
        {
            "id": "http://www.wikidata.org/entity/Q150229",
            "name": "Boxer Rebellion",
            "url": "http://en.wikipedia.org/wiki/Boxer%20Rebellion",
            "type": "EVENT",
            "salience": 0.18849252626174462
        },
        {
            "id": "http://www.wikidata.org/entity/Q40933",
            "name": "Eva Perón",
            "url": "http://en.wikipedia.org/wiki/Eva%20Per%C3%B3n",
            "type": "PERSON",
            "salience": 0.04924997690048171
        },
        {
            "id": "http://www.wikidata.org/entity/Q194419",
            "name": "Richard Branson",
            "url": "http://en.wikipedia.org/wiki/Richard%20Branson",
            "type": "PERSON",
            "salience": 0.04002915280926364
        },
        {
            "id": "http://www.wikidata.org/entity/Q8016",
            "name": "Winston Churchill",
            "url": "http://en.wikipedia.org/wiki/Winston%20Churchill",
            "type": "PERSON",
            "salience": 0.19588780470409425
        },
        {
            "id": "http://www.wikidata.org/entity/Q312",
            "name": "Apple Inc.",
            "url": "http://en.wikipedia.org/wiki/Apple%20Inc.",
            "type": "ORGANIZATION",
            "salience": 0.03250009246381493
        },
        {
            "id": "http://www.wikidata.org/entity/Q7322",
            "name": "Christopher Columbus",
            "url": "http://en.wikipedia.org/wiki/Christopher%20Columbus",
            "type": "PERSON",
            "salience": 0.1472183482855493
        },
        {
            "id": "http://www.wikidata.org/entity/Q82180",
            "name": "Mata Hari",
            "url": "http://en.wikipedia.org/wiki/Mata%20Hari",
            "type": "PERSON",
            "salience": 0.03990609079017187
        },
        {
            "id": "http://www.wikidata.org/entity/Q1189",
            "name": "Usain Bolt",
            "url": "http://en.wikipedia.org/wiki/Usain%20Bolt",
            "type": "PERSON",
            "salience": 0.036363176785911944
        },
        {
            "id": "http://www.wikidata.org/entity/Q12897",
            "name": "Pelé",
            "url": "http://en.wikipedia.org/wiki/Pel%C3%A9",
            "type": "PERSON",
            "salience": 0.044545089836870826
        },
        {
            "id": "http://www.wikidata.org/entity/Q10993",
            "name": "Tiger Woods",
            "url": "http://en.wikipedia.org/wiki/Tiger%20Woods",
            "type": "PERSON",
            "salience": 0.036363176785911944
        },
        {
            "id": "http://www.wikidata.org/entity/Q2831",
            "name": "Michael Jackson",
            "url": "http://en.wikipedia.org/wiki/Michael%20Jackson",
            "type": "PERSON",
            "salience": 0.029744020537019588
        },
        {
            "id": "http://www.wikidata.org/entity/Q45661",
            "name": "Coco Chanel",
            "url": "http://en.wikipedia.org/wiki/Coco%20Chanel",
            "type": "PERSON",
            "salience": 0.030217847453875263
        },
        {
            "id": "http://www.wikidata.org/entity/Q43247",
            "name": "Ingrid Bergman",
            "url": "http://en.wikipedia.org/wiki/Ingrid%20Bergman",
            "type": "PERSON",
            "salience": 0.030016932276861592
        },
        {
            "id": "http://www.wikidata.org/entity/Q9696",
            "name": "John F. Kennedy",
            "url": "http://en.wikipedia.org/wiki/John%20F.%20Kennedy",
            "type": "PERSON",
            "salience": 0.22541572871342258
        },
        {
            "id": "http://www.wikidata.org/entity/Q843",
            "name": "Pakistan",
            "url": "http://en.wikipedia.org/wiki/Pakistan",
            "type": "LOCATION",
            "salience": 0.04399273577386223
        },
        {
            "id": "http://www.wikidata.org/entity/Q11256",
            "name": "Fidel Castro",
            "url": "http://en.wikipedia.org/wiki/Fidel%20Castro",
            "type": "PERSON",
            "salience": 0.03180906964537964
        },
        {
            "id": "http://www.wikidata.org/entity/Q9215",
            "name": "Sigmund Freud",
            "url": "http://en.wikipedia.org/wiki/Sigmund%20Freud",
            "type": "PERSON",
            "salience": 0.036380263573960354
        },
        {
            "id": "http://www.wikidata.org/entity/Q3355",
            "name": "Amelia Earhart",
            "url": "http://en.wikipedia.org/wiki/Amelia%20Earhart",
            "type": "PERSON",
            "salience": 0.02827073469212947
        },
        {
            "id": "http://www.wikidata.org/entity/Q8007",
            "name": "Franklin D. Roosevelt",
            "url": "http://en.wikipedia.org/wiki/Franklin%20D.%20Roosevelt",
            "type": "PERSON",
            "salience": 0.06167412864616619
        },
        {
            "id": "http://www.wikidata.org/entity/Q34413",
            "name": "Benazir Bhutto",
            "url": "http://en.wikipedia.org/wiki/Benazir%20Bhutto",
            "type": "PERSON",
            "salience": 0.04599061474610047
        },
        {
            "id": "http://www.wikidata.org/entity/Q208141",
            "name": "Common Era",
            "url": "http://en.wikipedia.org/wiki/Common%20Era",
            "type": "OTHER",
            "salience": 0.04032853435593255
        },
        {
            "id": "http://www.wikidata.org/entity/Q15180",
            "name": "Soviet Union",
            "url": "http://en.wikipedia.org/wiki/Soviet%20Union",
            "type": "LOCATION",
            "salience": 0.037549640138542326
        },
        {
            "id": "http://www.wikidata.org/entity/Q41178",
            "name": "Haile Selassie",
            "url": "http://en.wikipedia.org/wiki/Haile%20Selassie",
            "type": "PERSON",
            "salience": 0.03968896162537203
        },
        {
            "id": "http://www.wikidata.org/entity/Q42786",
            "name": "Audrey Hepburn",
            "url": "http://en.wikipedia.org/wiki/Audrey%20Hepburn",
            "type": "PERSON",
            "salience": 0.036363176785911944
        },
        {
            "id": "http://www.wikidata.org/entity/Q33391",
            "name": "Leon Trotsky",
            "url": "http://en.wikipedia.org/wiki/Leon%20Trotsky",
            "type": "PERSON",
            "salience": 0.036528727842507665
        },
        {
            "id": "http://www.wikidata.org/entity/Q165421",
            "name": "Jacqueline Kennedy Onassis",
            "url": "http://en.wikipedia.org/wiki/Jacqueline%20Kennedy%20Onassis",
            "type": "PERSON",
            "salience": 0.0366832972606301
        },
        {
            "id": "http://www.wikidata.org/entity/Q9960",
            "name": "Ronald Reagan",
            "url": "http://en.wikipedia.org/wiki/Ronald%20Reagan",
            "type": "PERSON",
            "salience": 0.026817739190107583
        },
        {
            "id": "http://www.wikidata.org/entity/Q9682",
            "name": "Elizabeth II",
            "url": "http://en.wikipedia.org/wiki/Elizabeth%20II",
            "type": "PERSON",
            "salience": 0.23758613737123516
        },
        {
            "id": "http://www.wikidata.org/entity/Q4430",
            "name": "Cleopatra (1963 film)",
            "url": "http://en.wikipedia.org/wiki/Cleopatra%20%281963%20film%29",
            "type": "PERSON",
            "salience": 0.044741793814882864
        },
        {
            "id": "http://www.wikidata.org/entity/Q615",
            "name": "Lionel Messi",
            "url": "http://en.wikipedia.org/wiki/Lionel%20Messi",
            "type": "PERSON",
            "salience": 0.036528727842507665
        },
        {
            "id": "http://www.wikidata.org/entity/Q855",
            "name": "Joseph Stalin",
            "url": "http://en.wikipedia.org/wiki/Joseph%20Stalin",
            "type": "PERSON",
            "salience": 0.03413476200172744
        },
        {
            "id": "http://www.wikidata.org/entity/Q56016",
            "name": "Katharine Hepburn",
            "url": "http://en.wikipedia.org/wiki/Katharine%20Hepburn",
            "type": "PERSON",
            "salience": 0.03623613649907065
        },
        {
            "id": "http://www.wikidata.org/entity/Q1047",
            "name": "Jawaharlal Nehru",
            "url": "http://en.wikipedia.org/wiki/Jawaharlal%20Nehru",
            "type": "PERSON",
            "salience": 0.08239334777044145
        },
        {
            "id": "http://www.wikidata.org/entity/Q1203",
            "name": "John Lennon",
            "url": "http://en.wikipedia.org/wiki/John%20Lennon",
            "type": "PERSON",
            "salience": 0.03305827709057039
        }
    ]
}